[{"__type__":"cc.SpriteFrame","content":{"name":"kuoEnemy00","texture":"124f9d150","rect":[459,2,42,42],"offset":[0,0],"originalSize":[42,42]}},[{"__type__":"cc.Prefab","_name":"kuoEnemyPre","data":{"__id__":1},"asyncLoadAssets":null},{"__type__":"cc.Node","_name":"kuoEnemyPre","_components":[{"__type__":"cc.Sprite","node":{"__id__":1},"_spriteFrame":{"__uuid__":"9bhZaEv/hCvaCCU7Vs0KVk"}},{"__type__":"cc.BoxCollider","node":{"__id__":1},"_offset":{"__type__":"cc.Vec2","x":-2.3,"y":4.6},"_size":{"__type__":"cc.Size","width":30.9,"height":28}}],"_prefab":{"__type__":"cc.PrefabInfo","root":{"__id__":1},"asset":{"__uuid__":"afbJohhUVIOZqfU3HG2P5y"},"fileId":"f8mgkP3NFDOpzNF3sDNQVR"},"_contentSize":{"__type__":"cc.Size","width":42,"height":42},"_scaleX":2,"_scaleY":2,"_position":{"__type__":"cc.Vec2","x":5481,"y":1335},"groupIndex":3}]]